dtype_diet/__init__.py
dtype_diet/_modidx.py
dtype_diet/_nbdev.py
dtype_diet/core.py
dtype_diet-0.0.2.dist-info/LICENSE
dtype_diet-0.0.2.dist-info/METADATA
dtype_diet-0.0.2.dist-info/WHEEL
dtype_diet-0.0.2.dist-info/entry_points.txt
dtype_diet-0.0.2.dist-info/top_level.txt
dtype_diet-0.0.2.dist-info/RECORD
