Metadata-Version: 2.1
Name: dtype-diet
Version: 0.0.2
Summary: Attempt to shrink Pandas `dtypes` without losing data so you have more RAM (and maybe more speed)
Home-page: https://github.com/noklam/dtype_diet/tree/master/
Author: noklam
Author-email: mediumnok@gmail.com
License: MIT License
Keywords: pandas,optimization
Platform: UNKNOWN
Classifier: Development Status :: 3 - Alpha
Classifier: Intended Audience :: Developers
Classifier: License :: OSI Approved :: MIT License
Classifier: Natural Language :: English
Classifier: Programming Language :: Python :: 3.7
Classifier: Programming Language :: Python :: 3.8
Classifier: Programming Language :: Python :: 3.9
Classifier: Programming Language :: Python :: 3.10
Classifier: Programming Language :: Python :: 3.11
Requires-Python: >=3.7
License-File: LICENSE
Requires-Dist: pandas (>=1.0.0)
Requires-Dist: tabulate
